fibonacci/__init__.py
fibonacci/bin/__init__.py
pfibonacci-1.0.0.dist-info/LICENSE
pfibonacci-1.0.0.dist-info/METADATA
pfibonacci-1.0.0.dist-info/WHEEL
pfibonacci-1.0.0.dist-info/entry_points.txt
pfibonacci-1.0.0.dist-info/top_level.txt
pfibonacci-1.0.0.dist-info/RECORD
