Metadata-Version: 2.1
Name: pfibonacci
Version: 1.0.0
Summary: Python starter project
Home-page: https://github.com/amnivek/python-fibonacci
Author: Kevin Ma
Author-email: zhcnmk@gmail.com
License: MIT
Platform: UNKNOWN
License-File: LICENSE
